skilift/__init__.py
skilift/__main__.py
skilift/editfolder.py
skilift/editpage.py
skilift/editresponder.py
skilift/editsection.py
skilift/editvalidator.py
skilift/editwidget.py
skilift/fromjson.py
skilift/info_tuple.py
skilift/off_piste.py
skilift/utils.py
skilift/skiadmin/__init__.py
skilift/skiadmin/skiadmin/data/defaults.json
skilift/skiadmin/skiadmin/data/project.json
skilift/skiadmin/skiadmin/data/textblocks_json/en.json
skilift/skiadmin/skiadmin/static/logo.svg
skilift/skiadmin/skiadmin/static/logo_icon16.png
skilift/skiadmin/skiadmin/static/logo_icon16.svg
skilift/skiadmin/skiadminpackages/__init__.py
skilift/skiadmin/skiadminpackages/adminutils.py
skilift/skiadmin/skiadminpackages/css_styles.py
skilift/skiadmin/skiadminpackages/editcss/__init__.py
skilift/skiadmin/skiadminpackages/editcss/editcss.py
skilift/skiadmin/skiadminpackages/editfiles/__init__.py
skilift/skiadmin/skiadminpackages/editfiles/editfile.py
skilift/skiadmin/skiadminpackages/editfolders/__init__.py
skilift/skiadmin/skiadminpackages/editfolders/addfolder.py
skilift/skiadmin/skiadminpackages/editfolders/addpage.py
skilift/skiadmin/skiadminpackages/editfolders/editfolder.py
skilift/skiadmin/skiadminpackages/editfolders/editsite.py
skilift/skiadmin/skiadminpackages/editfolders/operations.py
skilift/skiadmin/skiadminpackages/editpages/__init__.py
skilift/skiadmin/skiadminpackages/editpages/common.py
skilift/skiadmin/skiadminpackages/editpages/editpage.py
skilift/skiadmin/skiadminpackages/editpages/inserts.py
skilift/skiadmin/skiadminpackages/editparts/__init__.py
skilift/skiadmin/skiadminpackages/editparts/editpart.py
skilift/skiadmin/skiadminpackages/editresponders/__init__.py
skilift/skiadmin/skiadminpackages/editresponders/editrespondpage.py
skilift/skiadmin/skiadminpackages/editsectionplaces/__init__.py
skilift/skiadmin/skiadminpackages/editsectionplaces/editplaceholder.py
skilift/skiadmin/skiadminpackages/editsections/__init__.py
skilift/skiadmin/skiadminpackages/editsections/inserts.py
skilift-0.1.4.dist-info/LICENSE
skilift-0.1.4.dist-info/WHEEL
skilift-0.1.4.dist-info/METADATA
skilift-0.1.4.dist-info/RECORD
