Metadata-Version: 2.1
Name: skilift
Version: 0.1.4
Summary: Development facility for the skipole WSGI Application generator
Keywords: wsgi,application,web,framework
Author-email: Bernard Czenkusz <bernie@skipole.co.uk>
Requires-Python: >=3.8
Classifier: License :: OSI Approved :: MIT License
Classifier: Operating System :: OS Independent
Classifier: Topic :: Internet :: WWW/HTTP :: WSGI :: Application
Requires-Dist: skipole>=5.6.0
Project-URL: Documentation, https://bernie-skipole.github.io/skipole/
Project-URL: Source, https://github.com/bernie-skipole/skilift
